{
  "hotdog_shops": [
    {
      "id": "1",
      "name_shop": "Street Hotdog",
      "location": "Thomesheiveien 33, 3770 Kragerø",
      "image": "https://images.unsplash.com/photo-1533929736458-ca588d08c8be?ixlib=rb-4.0.3&ixid=MnwxMjA3fDB8MHxwaG90by1wYWdlfHx8fGVufDB8fHx8&auto=format&fit=crop&w=1170&q=80",
      "rating_stars": "5"
    },
    {
      "id": "2",
      "title": "Hotdogs & Burgers",
      "location": "Torvgata 18, 3770 Kragerø",
      "image": "https://images.unsplash.com/photo-1506146332389-18140dc7b2fb?ixlib=rb-4.0.3&ixid=MnwxMjA3fDB8MHxwaG90by1wYWdlfHx8fGVufDB8fHx8&auto=format&fit=crop&w=764&q=80",
      "rating_stars": "4"
    },
    {
      "id": "3",
      "title": "Hotdogs Friends",
      "location": "Andølingen 6, 3770 Kragerø",
      "image": "https://images.unsplash.com/photo-1579282240050-352db0a14c21?ixlib=rb-4.0.3&ixid=MnwxMjA3fDB8MHxwaG90by1wYWdlfHx8fGVufDB8fHx8&auto=format&fit=crop&w=652&q=80",
      "rating_stars": "3"
    }
  ]
}
